odoo10_addon_account_asset_depr_line_cancel-10.0.1.0.0-py2.7-nspkg.pth
odoo/addons/account_asset_depr_line_cancel/README.rst
odoo/addons/account_asset_depr_line_cancel/__init__.py
odoo/addons/account_asset_depr_line_cancel/__manifest__.py
odoo/addons/account_asset_depr_line_cancel/models/__init__.py
odoo/addons/account_asset_depr_line_cancel/models/account_asset_asset.py
odoo/addons/account_asset_depr_line_cancel/static/description/icon.png
odoo/addons/account_asset_depr_line_cancel/static/description/icon.svg
odoo/addons/account_asset_depr_line_cancel/views/account_asset_asset_view.xml
odoo10_addon_account_asset_depr_line_cancel-10.0.1.0.0.dist-info/DESCRIPTION.rst
odoo10_addon_account_asset_depr_line_cancel-10.0.1.0.0.dist-info/METADATA
odoo10_addon_account_asset_depr_line_cancel-10.0.1.0.0.dist-info/RECORD
odoo10_addon_account_asset_depr_line_cancel-10.0.1.0.0.dist-info/WHEEL
odoo10_addon_account_asset_depr_line_cancel-10.0.1.0.0.dist-info/metadata.json
odoo10_addon_account_asset_depr_line_cancel-10.0.1.0.0.dist-info/namespace_packages.txt
odoo10_addon_account_asset_depr_line_cancel-10.0.1.0.0.dist-info/top_level.txt
